{
  "url": "https://docs.base.org/base-chain/tools/account-abstraction",
  "title": "Account Abstraction - Base Documentation",
  "scraped_at": "2026-02-04T10:27:14.019690",
  "headings": [
    {
      "level": "h2",
      "text": "​Alchemy Account Kit"
    },
    {
      "level": "h2",
      "text": "​Biconomy"
    },
    {
      "level": "h2",
      "text": "​Coinbase Account Abstraction Kit"
    },
    {
      "level": "h2",
      "text": "​Openfort"
    },
    {
      "level": "h2",
      "text": "​Pimlico"
    },
    {
      "level": "h2",
      "text": "​Reown (prev. known as WalletConnect)"
    },
    {
      "level": "h2",
      "text": "​Safe"
    },
    {
      "level": "h2",
      "text": "​Stackup"
    },
    {
      "level": "h2",
      "text": "​thirdweb"
    },
    {
      "level": "h2",
      "text": "​WalletKit"
    },
    {
      "level": "h2",
      "text": "​ZeroDev"
    }
  ],
  "content": "Base Documentation home pageSearch...⌘KAsk AISearch...NavigationToolsAccount AbstractionGet StartedBase ChainBase AccountBase AppMini AppsOnchainKitCookbookShowcaseLearnGitHubStatusChain StatsExplorerSupportBlogQuickstartWhy Base?Deploy on BaseConnecting to BaseBase-Mainnet BridgeBase-Solana BridgeNetwork InformationBase ContractsEcosystem ContractsNetwork FeesBlock BuildingTransaction FinalityDifferences: Ethereum & BaseTroubleshooting TransactionsConfiguration ChangelogFlashblocksAppsNode ProvidersFlashblocks FAQNode OperatorsGetting StartedPerformance TuningSnapshotsTroubleshootingBuilder CodesBase Builder CodesBuilder Codes FAQToolsBase ProductsOnchain Registry APINode ProvidersBlock ExplorersNetwork FaucetsOraclesUser OnboardingData IndexersCross-chainAccount AbstractionOnrampsTokens in Coinbase WalletSecuritySecurity Council for BaseAvoid Malicious FlagsReport a VulnerabilityOn this pageAlchemy Account KitBiconomyCoinbase Account Abstraction KitOpenfortPimlicoReown (prev. known as WalletConnect)SafeStackupthirdwebWalletKitZeroDev​Alchemy Account Kit\nAccount Kit is a complete solution for account abstraction. Using Account Kit, you can create a smart contract wallet for every user that leverages account abstraction to simplify every step of your app’s onboarding experience. It also offers Gas Manager and Bundler APIs for sponsoring gas and batching transactions.\n​Biconomy\nBiconomy is an Account Abstraction toolkit that enables you to provide the simplest UX for your dapp or wallet. It offers modular smart accounts, as well as paymasters and bundlers as a service for sponsoring gas and executing transactions at scale.\n​Coinbase Account Abstraction Kit\nThe Coinbase Developer Platform Account Abstraction Kit is an account abstraction toolkit for building simple onchain user experiences. Account Abstraction Kit provides a paymaster and bundler that allows you to sponsor gas fees and bundle user transactions, improving the user experience of your application.\n​Openfort\nOpenfort is an infrastructure provider designed to simplify the development of games and gamified experiences across their suite of API endpoints. The platform vertically integrates the AA stack, so game developers can focus on game development without worrying about private key management, the account model or the onchain interactions with paymasters and bundlers. The Openfort platform is compatible with most EVM chains, including Base.\n​Pimlico\nPimlico provides an infrastructure platform that makes building smart accounts simpler. If you are developing, an ERC-4337 smart account, they provide bundlers, verifying paymasters, ERC-20 paymasters, and much more.\n​Reown (prev. known as WalletConnect)\nReown gives developers the tools to build user experiences that make digital ownership effortless, intuitive, and secure. One of Reown’s offerings is the AppKit SDK.\nAppKit is a powerful, free, and fully open-source SDK for developers looking to integrate wallet connections and other Web3 functionalities into their apps on any EVM and non-EVM chain. In just a few simple steps, you can provide your users with seamless wallet access, one-click authentication, social logins, and notifications—streamlining their experience while enabling advanced features like on-ramp functionality, in-app token swaps and smart accounts. Check out the docs to get started.\n​Safe\nSafe provides modular smart account infrastructure and account abstraction stack via their Safe Account Abstraction SDK, API, and Protocol.\n​Stackup\nStackup provides smart account tooling for building account abstraction within your apps. They offer Paymaster and Bundler APIs for sponsoring gas and sending account abstraction transactions.\n​thirdweb\nthirdweb offers the complete toolkit to leverage account abstraction technology to enable seamless user experiences for your users. This includes Account Factory contracts that let your users spin up Smart Accounts, Bundler for UserOps support, and Paymaster to enable gas sponsorships.\n​WalletKit\nWalletKit is an all-in-one platform for adding smart, gasless wallets to your app. It has integrated support for ERC 4337 and comes with a paymaster and bundler included, requiring no extra setup.\nWalletKit also offers pre-built components for onboarding users with email and social logins, which can be integrated in under 15 minutes using their React SDK or the wagmi connector. Alternatively, build completely bespoke experiences for your users using WalletKit’s Wallets API.\nWalletKit is compatible with most EVM chains, including Base. You can check out the WalletKit documentation here. Start building for free on the Base testnet today.\n​ZeroDev\nZeroDev is an embedded wallet powered by account abstraction. It offers you the ability to create self-custody wallets for your users, sponsor gas, and simplify user flows by batching and automating transactions.Was this page helpful?YesNoSuggest editsRaise issueCross-chainPreviousOnrampsNext⌘I",
  "code_blocks": [],
  "links": [
    {
      "text": "Skip to main content",
      "url": "https://docs.base.org/base-chain/tools/account-abstraction#content-area"
    },
    {
      "text": "Base Documentationhome page",
      "url": "https://docs.base.org/"
    },
    {
      "text": "Get Started",
      "url": "https://docs.base.org/get-started/base"
    },
    {
      "text": "Base Chain",
      "url": "https://docs.base.org/base-chain/quickstart/why-base"
    },
    {
      "text": "Base Account",
      "url": "https://docs.base.org/base-account/overview/what-is-base-account"
    },
    {
      "text": "Base App",
      "url": "https://docs.base.org/base-app/introduction/beta-faq"
    },
    {
      "text": "Mini Apps",
      "url": "https://docs.base.org/mini-apps/quickstart/migrate-existing-apps"
    },
    {
      "text": "OnchainKit",
      "url": "https://docs.base.org/onchainkit/latest/getting-started/overview"
    },
    {
      "text": "Cookbook",
      "url": "https://docs.base.org/cookbook/onboard-any-user"
    },
    {
      "text": "Showcase",
      "url": "https://docs.base.org/showcase"
    },
    {
      "text": "Learn",
      "url": "https://docs.base.org/learn/welcome"
    },
    {
      "text": "Status",
      "url": "https://status.base.org/"
    },
    {
      "text": "Chain Stats",
      "url": "https://www.base.org/stats"
    },
    {
      "text": "Why Base?",
      "url": "https://docs.base.org/base-chain/quickstart/why-base"
    },
    {
      "text": "Deploy on Base",
      "url": "https://docs.base.org/base-chain/quickstart/deploy-on-base"
    },
    {
      "text": "Connecting to Base",
      "url": "https://docs.base.org/base-chain/quickstart/connecting-to-base"
    },
    {
      "text": "Base-Mainnet Bridge",
      "url": "https://docs.base.org/base-chain/quickstart/bridge-token"
    },
    {
      "text": "Base-Solana Bridge",
      "url": "https://docs.base.org/base-chain/quickstart/base-solana-bridge"
    },
    {
      "text": "Base Contracts",
      "url": "https://docs.base.org/base-chain/network-information/base-contracts"
    },
    {
      "text": "Ecosystem Contracts",
      "url": "https://docs.base.org/base-chain/network-information/ecosystem-contracts"
    },
    {
      "text": "Network Fees",
      "url": "https://docs.base.org/base-chain/network-information/network-fees"
    },
    {
      "text": "Block Building",
      "url": "https://docs.base.org/base-chain/network-information/block-building"
    },
    {
      "text": "Transaction Finality",
      "url": "https://docs.base.org/base-chain/network-information/transaction-finality"
    },
    {
      "text": "Differences: Ethereum & Base",
      "url": "https://docs.base.org/base-chain/network-information/diffs-ethereum-base"
    },
    {
      "text": "Troubleshooting Transactions",
      "url": "https://docs.base.org/base-chain/network-information/troubleshooting-transactions"
    },
    {
      "text": "Configuration Changelog",
      "url": "https://docs.base.org/base-chain/network-information/configuration-changelog"
    },
    {
      "text": "Apps",
      "url": "https://docs.base.org/base-chain/flashblocks/apps"
    },
    {
      "text": "Node Providers",
      "url": "https://docs.base.org/base-chain/flashblocks/node-providers"
    },
    {
      "text": "Flashblocks FAQ",
      "url": "https://docs.base.org/base-chain/flashblocks/docs"
    },
    {
      "text": "Getting Started",
      "url": "https://docs.base.org/base-chain/node-operators/run-a-base-node"
    },
    {
      "text": "Performance Tuning",
      "url": "https://docs.base.org/base-chain/node-operators/performance-tuning"
    },
    {
      "text": "Snapshots",
      "url": "https://docs.base.org/base-chain/node-operators/snapshots"
    },
    {
      "text": "Troubleshooting",
      "url": "https://docs.base.org/base-chain/node-operators/troubleshooting"
    },
    {
      "text": "Base Builder Codes",
      "url": "https://docs.base.org/base-chain/builder-codes/builder-codes"
    },
    {
      "text": "Builder Codes FAQ",
      "url": "https://docs.base.org/base-chain/builder-codes/builder-codes-faq"
    },
    {
      "text": "Base Products",
      "url": "https://docs.base.org/base-chain/tools/base-products"
    },
    {
      "text": "Onchain Registry API",
      "url": "https://docs.base.org/base-chain/tools/onchain-registry-api"
    },
    {
      "text": "Node Providers",
      "url": "https://docs.base.org/base-chain/tools/node-providers"
    },
    {
      "text": "Block Explorers",
      "url": "https://docs.base.org/base-chain/tools/block-explorers"
    },
    {
      "text": "Network Faucets",
      "url": "https://docs.base.org/base-chain/tools/network-faucets"
    },
    {
      "text": "Oracles",
      "url": "https://docs.base.org/base-chain/tools/oracles"
    },
    {
      "text": "User Onboarding",
      "url": "https://docs.base.org/base-chain/tools/onboarding"
    },
    {
      "text": "Data Indexers",
      "url": "https://docs.base.org/base-chain/tools/data-indexers"
    },
    {
      "text": "Cross-chain",
      "url": "https://docs.base.org/base-chain/tools/cross-chain"
    },
    {
      "text": "Account Abstraction",
      "url": "https://docs.base.org/base-chain/tools/account-abstraction"
    },
    {
      "text": "Onramps",
      "url": "https://docs.base.org/base-chain/tools/onramps"
    },
    {
      "text": "Tokens in Coinbase Wallet",
      "url": "https://docs.base.org/base-chain/tools/tokens-in-wallet"
    },
    {
      "text": "Security Council for Base",
      "url": "https://docs.base.org/base-chain/security/security-council"
    },
    {
      "text": "Avoid Malicious Flags",
      "url": "https://docs.base.org/base-chain/security/avoid-malicious-flags"
    },
    {
      "text": "Report a Vulnerability",
      "url": "https://docs.base.org/base-chain/security/report-vulnerability"
    },
    {
      "text": "Alchemy Account Kit",
      "url": "https://docs.base.org/base-chain/tools/account-abstraction#alchemy-account-kit"
    },
    {
      "text": "Biconomy",
      "url": "https://docs.base.org/base-chain/tools/account-abstraction#biconomy"
    },
    {
      "text": "Coinbase Account Abstraction Kit",
      "url": "https://docs.base.org/base-chain/tools/account-abstraction#coinbase-account-abstraction-kit"
    },
    {
      "text": "Openfort",
      "url": "https://docs.base.org/base-chain/tools/account-abstraction#openfort"
    },
    {
      "text": "Pimlico",
      "url": "https://docs.base.org/base-chain/tools/account-abstraction#pimlico"
    },
    {
      "text": "Reown (prev. known as WalletConnect)",
      "url": "https://docs.base.org/base-chain/tools/account-abstraction#reown-prev-known-as-walletconnect"
    },
    {
      "text": "Safe",
      "url": "https://docs.base.org/base-chain/tools/account-abstraction#safe"
    },
    {
      "text": "Stackup",
      "url": "https://docs.base.org/base-chain/tools/account-abstraction#stackup"
    },
    {
      "text": "thirdweb",
      "url": "https://docs.base.org/base-chain/tools/account-abstraction#thirdweb"
    },
    {
      "text": "WalletKit",
      "url": "https://docs.base.org/base-chain/tools/account-abstraction#walletkit"
    },
    {
      "text": "ZeroDev",
      "url": "https://docs.base.org/base-chain/tools/account-abstraction#zerodev"
    },
    {
      "text": "​",
      "url": "https://docs.base.org/base-chain/tools/account-abstraction#alchemy-account-kit"
    },
    {
      "text": "​",
      "url": "https://docs.base.org/base-chain/tools/account-abstraction#biconomy"
    },
    {
      "text": "​",
      "url": "https://docs.base.org/base-chain/tools/account-abstraction#coinbase-account-abstraction-kit"
    },
    {
      "text": "​",
      "url": "https://docs.base.org/base-chain/tools/account-abstraction#openfort"
    },
    {
      "text": "​",
      "url": "https://docs.base.org/base-chain/tools/account-abstraction#pimlico"
    },
    {
      "text": "​",
      "url": "https://docs.base.org/base-chain/tools/account-abstraction#reown-prev-known-as-walletconnect"
    },
    {
      "text": "​",
      "url": "https://docs.base.org/base-chain/tools/account-abstraction#safe"
    },
    {
      "text": "​",
      "url": "https://docs.base.org/base-chain/tools/account-abstraction#stackup"
    },
    {
      "text": "​",
      "url": "https://docs.base.org/base-chain/tools/account-abstraction#thirdweb"
    },
    {
      "text": "​",
      "url": "https://docs.base.org/base-chain/tools/account-abstraction#walletkit"
    },
    {
      "text": "​",
      "url": "https://docs.base.org/base-chain/tools/account-abstraction#zerodev"
    },
    {
      "text": "Cross-chainPrevious",
      "url": "https://docs.base.org/base-chain/tools/cross-chain"
    },
    {
      "text": "OnrampsNext",
      "url": "https://docs.base.org/base-chain/tools/onramps"
    }
  ]
}